phondler/__init__.py
phondler/phondler.py
phondler/phondler_tables.py
phondler/phoneme.py
phondler/pronlex.py
phondler-0.0.3.dist-info/LICENSE
phondler-0.0.3.dist-info/METADATA
phondler-0.0.3.dist-info/WHEEL
phondler-0.0.3.dist-info/top_level.txt
phondler-0.0.3.dist-info/RECORD
