Metadata-Version: 2.1
Name: phondler
Version: 0.0.3
Summary: Python phonetic handler
Home-page: https://github.com/fsbayer/phondler
Author: Frederic Bayer
Author-email: frederic.s.bayer@gmail.com
License: MIT License
Project-URL: Bug Tracker, https://github.com/pypa/sampleproject/issues
Platform: UNKNOWN
Classifier: Programming Language :: Python :: 3
Classifier: License :: OSI Approved :: MIT License
Classifier: Operating System :: OS Independent
Classifier: Development Status :: 1 - Planning
Classifier: Intended Audience :: Developers
Classifier: Intended Audience :: Education
Classifier: Intended Audience :: Science/Research
Classifier: Topic :: Artistic Software
Classifier: Topic :: Education
Classifier: Topic :: Text Processing :: Linguistic
Classifier: Topic :: Scientific/Engineering
Classifier: Topic :: Software Development :: Libraries :: Python Modules
Classifier: Topic :: Utilities
Requires-Python: >=3.9
License-File: LICENSE
